[
    {
        "name": "Taylor Carroll",
        "githubHandle": "taylorhcarroll"
    },
    {
        "name": "David Cornish",
        "githubHandle": "dcornish84"
    },
    {
        "name": "Ken Dixon",
        "githubHandle": "ktdixon2"
    },
    {
        "name": "Gradi Ellis",
        "githubHandle": "geellis1"
    },
    {
        "name": "Dylan Griffith",
        "githubHandle": "DylPickle11"
    },
    {
        "name": "Phil Griswold",
        "githubHandle": "Philgriswold"
    },
    {
        "name": "Sage Klein",
        "githubHandle": "sageklein"
    },
    {
        "name": "Summer Liddington",
        "githubHandle": "summerliddington"
    },
    {
        "name": "Laura Maxwell",
        "githubHandle": "laurenelizamax"
    },
    {
        "name": "Mark McCann",
        "githubHandle": "mjmccann90"
    },
    {
        "name": "James McClarty",
        "githubHandle": "JamesMcClarty"
    },
    {
        "name": "Olexandr Momotyuk",
        "githubHandle": "omomotyuk"
    },
    {
        "name": "Fortunato Mugnano",
        "githubHandle": "FortunatoMugnano"
    },
    {
        "name": "Seth Oakley",
        "githubHandle": "sethoak"
    },
    {
        "name": "Elizabeth Pence",
        "githubHandle": "emirnda"
    },
    {
        "name": "Ethan Pierrte",
        "githubHandle": "WitheredFlame"
    },
    {
        "name": "Leigh Rogers",
        "githubHandle": "leighmrogers"
    },
    {
        "name": "stephen senft",
        "githubHandle": "stephensenft21"
    },
    {
        "name": "Shirish Sherstha",
        "githubHandle": "sls-coderepo"
    },
    {
        "name": "Heidi Smith",
        "githubHandle": "hspradlin8"
    },
    {
        "name": "Quin Smith",
        "githubHandle": "JQuinSmith"
    },
    {
        "name": "Chandler Turner",
        "githubHandle": "jchandlerturner"
    },
    {
        "name": "Nate Vogel",
        "githubHandle": "navogel"
    },
    {
        "name": "Aryn Weatherly",
        "githubHandle": "Arynweatherly"
    },
    {
        "name": "Nicholas Wessel",
        "githubHandle": "wesseln1"
    },
    {
        "name": "keaton williamson",
        "githubHandle": "keatonwilliamson"
    },
    {
        "name": "George Kelley",
        "githubHandle": "geokelleyh"
    }
]